LICENSE
README.rst
setup.py
ltce/__init__.py
ltce.egg-info/PKG-INFO
ltce.egg-info/SOURCES.txt
ltce.egg-info/dependency_links.txt
ltce.egg-info/requires.txt
ltce.egg-info/top_level.txt
ltce/eval/__init__.py
ltce/eval/metrics.py
ltce/example/__init__.py
ltce/example/ctransformer.py
ltce/example/laser.py
ltce/example/ltee.py
ltce/example/rtransformer.py
ltce/example/sind_dlinear.py
ltce/example/sind_linear.py
ltce/example/sind_mlp.py
ltce/model/__init__.py
ltce/model/ctransformer.py
ltce/model/laser.py
ltce/model/ltee.py
ltce/model/rtransformer.py
ltce/model/sind.py
ltce/utils/__init__.py
ltce/utils/dataset.py
ltce/utils/loss.py
ltce/utils/splitter.py